{
  "id": 652,
  "book": "Genesis",
  "chapter": 22,
  "verse": 4,
  "slug": "genesis-22-4",
  "testament": "Old Testament",
  "text": "Then on the third day Abraham lifted up his eyes, and saw the place afar off.",
  "text_kjv": "Then on the third day Abraham lifted up his eyes, and saw the place afar off.",
  "text_niv": "On the third day Abraham looked up and saw the place in the distance.",
  "text_esv": "On the third day Abraham lifted up his eyes and saw the place from afar.",
  "text_nlt": "On the third day of their journey, Abraham looked up and saw the place in the distance.",
  "text_msg": "On the third day he looked up and saw the place in the distance.",
  "text_nasb": "On the third day Abraham raised his eyes and saw the place from a distance.",
  "context": "Genesis 22:4, 'Then on the third day Abraham lifted up his eyes, and saw the place afar off,' is a pivotal point in the narrative of Abraham's near sacrifice of Isaac. Understanding the historical and cultural setting illuminates the weight of this verse. Journeys in the ancient Near East were not swift or comfortable. Three days of travel on foot, with a loaded donkey and servants, would have been arduous, testing Abraham's physical and emotional endurance. The terrain of Moriah was likely hilly and rugged, making the ascent challenging. The 'place afar off' was likely a prominent peak, visible from a distance, yet still requiring considerable effort to reach. The mention of 'the third day' is significant. It suggests a period of prolonged reflection and potential wavering. Time allowed Abraham ample opportunity to reconsider his decision, yet he persevered. The ancient world valued obedience to deities, but human sacrifice, while practiced in some cultures, was increasingly frowned upon in Abraham's time. This tension between perceived divine command and burgeoning moral sensibilities would have intensified Abraham's internal struggle. Abraham's society emphasized patriarchal authority and the importance of progeny. Sacrificing Isaac, his promised heir, went against the very grain of his cultural expectations and threatened the fulfillment of God's covenant. Finally, considering the limited perspective of individuals in that era is crucial. Abraham lacked the full understanding of God's plan that we have today. His faith was being tested to its absolute limit, demanding complete trust in a God whose ways were, at that moment, utterly incomprehensible.",
  "meaning": "Theologically, Genesis 22:4 is laden with significance. The 'third day' resonates with themes of resurrection and new beginnings, prefiguring the resurrection of Jesus Christ. Just as Abraham's faith was rewarded with Isaac's life being spared, believers find new life through Christ's sacrifice. The phrase 'lifted up his eyes' suggests a moment of renewed hope and divine revelation. Despite the unimaginable horror he faced, Abraham's gaze, both physically and spiritually, was directed towards God's provision. It symbolizes a conscious choice to trust in God's goodness, even when circumstances appeared utterly bleak. The 'place afar off' can be interpreted as a metaphor for the sometimes-distant nature of God's promises. Faith often requires perseverance and patient waiting, trusting that God's plan will unfold in His timing, even when the destination seems remote. Abraham's willingness to sacrifice Isaac reveals the depth of his faith and obedience, which are central tenets of the Abrahamic covenant. This verse highlights the tension between divine sovereignty and human agency. Abraham was called to obey God's command, yet God ultimately intervened, demonstrating His own sovereignty over life and death. God’s provision of the ram as a substitute for Isaac foreshadows the ultimate substitutionary sacrifice of Jesus Christ, who atoned for the sins of humanity. Abraham's willingness to offer his only son serves as a powerful illustration of God's immeasurable love in offering His own Son for the salvation of the world. The 'seeing' in this verse is not merely a physical act, but a spiritual one. Abraham 'saw' the place in the sense that he perceived God's presence and potential provision, even before he fully understood His plan. This spiritual discernment is a hallmark of genuine faith.",
  "application": "Genesis 22:4 presents several practical applications for modern believers. First, it reminds us of the importance of perseverance in faith. Like Abraham, we will face trials that test our trust in God. The 'third day' experience teaches us to keep moving forward, even when the path ahead seems difficult and the destination seems distant. Second, it encourages us to maintain a hopeful outlook, even in the midst of suffering. Abraham 'lifted up his eyes,' choosing to focus on God's potential provision rather than succumbing to despair. We can cultivate this same attitude by intentionally directing our thoughts towards God's promises and seeking His perspective in challenging situations. Third, it challenges us to examine the 'idols' in our own lives – those things we hold more dear than God. Are we willing to sacrifice our comfort, our possessions, or even our dreams, if God asks us to? This verse prompts us to re-evaluate our priorities and ensure that God occupies the central place in our hearts. Fourth, it emphasizes the importance of obedience. While God may not ask us to make literal sacrifices like Abraham, He does call us to obey His commands and follow His leading, even when it doesn't make sense to us. This requires surrendering our own will and trusting in God's wisdom. Fifth, it encourages us to cultivate spiritual discernment. Like Abraham, we need to develop the ability to 'see' God's presence and potential provision in the midst of difficulty. This comes through prayer, studying God's Word, and seeking His guidance in all aspects of our lives. It's a reminder that God's timing isn't always our timing, and we must learn to trust in His divine plan, even when it seems distant or unclear. Embrace the 'third day' principle; after enduring hardship, anticipate God's revelation and breakthrough.",
  "prayer": "Lord, help me to have the faith of Abraham, to trust You even when I don't understand Your ways. Grant me the perseverance to keep moving forward, even when the journey is long and difficult. Open my eyes to see Your presence and provision in the midst of my trials. Help me to lift my gaze beyond my immediate circumstances and fix my eyes on You. Reveal to me any idols in my life that I hold more dear than You, and give me the courage to surrender them completely. Strengthen my obedience to Your commands and guide me with Your wisdom. Thank you for the ultimate sacrifice of Your Son, Jesus Christ. In His name I pray, Amen.",
  "faqs": [
    {
      "answer": "The phrase 'third day' in Genesis 22:4 is significant for several reasons. It implies a period of testing and waiting, common in biblical narratives. It foreshadows themes of resurrection and deliverance seen later in Scripture, particularly the resurrection of Jesus on the third day, signifying new hope and victory after suffering. The prolonged journey also served to test Abraham's resolve.",
      "question": "Q1 about this verse: Why is the third day specifically mentioned?"
    },
    {
      "answer": "To 'lift up your eyes' suggests a shift in perspective, both physically and spiritually. It implies a conscious decision to look beyond immediate circumstances and to focus on a broader horizon, in Abraham's case, towards the 'place' appointed by God. It symbolizes hope and anticipation despite the challenge.",
      "question": "Q2: What does it mean to 'lift up your eyes' in this context?"
    },
    {
      "answer": "The 'place afar off' can represent God's promises that seem distant or unattainable. It signifies the future blessings and goals that require faith, perseverance, and trust in God's timing. We can relate to it by acknowledging that sometimes, God's plan unfolds gradually, requiring patience.",
      "question": "Q3: How can we relate to Abraham's 'place afar off' today?"
    },
    {
      "answer": "This verse implicitly teaches that God's timing is often different from our own. The three-day journey emphasizes the importance of patience and endurance while waiting for God's plan to unfold. It reinforces the idea that God's purposes are always working, even when we can't see them immediately.",
      "question": "Q4: What does this verse teach us about God's timing?"
    },
    {
      "answer": "Abraham's obedience serves as a model for believers today. While we may not face the same extreme test, we are called to obey God's commands and trust in His leading, even when it's difficult or doesn't make sense. His faith demonstrates the importance of submission to God's will.",
      "question": "Q5: How does Abraham's obedience relate to our own faith journey?"
    }
  ],
  "popularity_score": 0,
  "exportedAt": "2026-02-20T16:42:49.982Z"
}