{
  "id": 15911,
  "book": "Psalms",
  "chapter": 107,
  "verse": 6,
  "slug": "psalms-107-6",
  "testament": "Old Testament",
  "text": "Then they cried unto the LORD in their trouble, and he delivered them out of their distresses.",
  "text_kjv": "Then they cried unto the LORD in their trouble, and he delivered them out of their distresses.",
  "text_niv": "Then they cried out to the Lord in their trouble,and he delivered them from their distress.",
  "text_esv": "Then they cried to the LORD in their trouble, and he delivered them from their distress.",
  "text_nlt": "“LORD, help!” they cried in their trouble,and he rescued them from their distress.",
  "text_msg": "Then, in your desperate condition, you called out to God.He got you out in the nick of time;",
  "text_nasb": "Then they cried out to the LORD in their trouble; He delivered them out of their distresses.",
  "context": "Psalm 107 is a song of thanksgiving, likely used in temple worship after the return of the Israelites from the Babylonian exile. The psalm follows a repetitive structure, highlighting various situations of distress followed by God's deliverance. The cultural backdrop involves a deeply rooted understanding of covenant theology. God's faithfulness to his promises to Abraham, Isaac, and Jacob was paramount. The exile was seen as a consequence of national sin, a breach of the covenant. The return, therefore, was viewed as an act of God's grace and renewed covenantal commitment. The situations described – wandering in the desert, imprisonment, sickness, and storms at sea – are not merely individual hardships but represent the collective experiences of the nation. The 'trouble' and 'distress' mentioned were not abstract concepts; they were real, tangible hardships impacting the entire community. In ancient Near Eastern cultures, communal well-being was prioritized, making national restoration a deeply personal experience for each individual. The act of 'crying out to the Lord' reflected a desperation born out of utter helplessness, a complete reliance on divine intervention. The phrase resonates with the pleas of the Israelites in Egypt and other moments of national crisis throughout their history. The imagery of deliverance is crucial; it signifies not just escape from hardship but restoration to a state of wholeness and blessing within the covenant relationship with God. The cyclical structure of the psalm reinforces the idea that God's saving power is perpetually available to those who call upon him in genuine need.",
  "meaning": "Psalm 107:6 encapsulates the core theological message of the entire psalm: God hears and responds to the cries of his people. The verse highlights the inherent brokenness of humanity and our dependence on divine intervention. 'Trouble' and 'distresses' are presented as inevitable realities of life in a fallen world, representing the myriad challenges – physical, emotional, spiritual – that individuals and communities face. The act of 'crying unto the Lord' is not presented as a mere formality but as a genuine outpouring of desperation and faith. It signifies acknowledging God as the ultimate source of help and surrendering control to his sovereign will. The word 'Lord' (YHWH) itself is significant, invoking the covenant name of God, reminding the people of his unwavering commitment to them. 'He delivered them' underscores the active and personal involvement of God in the lives of his people. Deliverance is not merely an abstract concept; it is a tangible reality experienced through God's intervention. The word 'delivered' also implies a complete and comprehensive rescue, not just temporary relief but a lasting transformation. This verse points to the grace and mercy of God, who responds to the cries of even the most undeserving. It highlights the importance of prayer as a vital means of connecting with God and experiencing his power. The verse also foreshadows the ultimate deliverance offered through Jesus Christ, who rescues humanity from the ultimate distress – sin and death. The cycle of distress and deliverance prefigures the Christian understanding of suffering followed by redemption.",
  "application": "Psalm 107:6 provides a timeless and relevant message for modern believers facing a variety of challenges. In a world filled with uncertainty, anxiety, and suffering, this verse offers a beacon of hope and a reminder of God's unwavering presence. Practically, it encourages us to cultivate a habit of prayer, not as a last resort but as a primary means of communicating with God. When facing personal struggles, relationship difficulties, financial hardships, or spiritual battles, the first response should be to 'cry unto the Lord.' This involves not only uttering words of prayer but also engaging in honest and heartfelt communication with God, expressing our needs, fears, and vulnerabilities. We must also remember that 'crying unto the Lord' requires humility and a willingness to surrender control to his will. It means acknowledging that we don't have all the answers and trusting that God's plan for our lives is ultimately good, even when we don't understand it. This verse challenges the modern tendency towards self-reliance and encourages us to embrace our dependence on God. It also reminds us that we are not alone in our struggles; God is always present and willing to help. Sharing our burdens with trusted friends and family members can also provide support and encouragement during difficult times. Furthermore, this verse can be applied to broader social issues. As Christians, we are called to advocate for justice, compassion, and mercy in a world plagued by poverty, oppression, and injustice. Crying out to the Lord on behalf of others and actively working to alleviate their suffering is a practical way of living out the message of Psalm 107:6. Finally, we should cultivate a spirit of gratitude, remembering to thank God for his past deliverances and trusting that he will continue to be faithful in the future. Sharing testimonies of God's faithfulness with others can also inspire hope and encourage them to seek him in their own times of trouble.",
  "prayer": "Heavenly Father, I come before you with a humble heart, acknowledging my dependence on your grace and mercy. I thank you for the promise in Psalm 107:6, that you hear and respond to the cries of your people. Lord, I confess that I often try to handle my problems on my own, forgetting to turn to you in prayer. Forgive me for my self-reliance and help me to cultivate a habit of seeking your guidance in all areas of my life. I lift up my current struggles to you (mention specific struggles). I pray for your wisdom, strength, and peace to navigate these challenges. I trust that you will deliver me from my distresses, according to your perfect will. Help me to be patient and to wait on your timing. Remind me of your faithfulness in the past, and give me hope for the future. I also pray for those who are suffering around the world, that they may find comfort and hope in you. In Jesus' name, I pray. Amen.",
  "faqs": [
    {
      "answer": "No, Psalm 107:6 doesn't guarantee immediate relief. While God hears and answers, his timing and methods differ. Sometimes deliverance is swift, other times it involves enduring trials with his support. His response always aligns with his greater purpose and our spiritual growth.",
      "question": "Q1 about this verse: Does Psalm 107:6 guarantee instant relief from all troubles?"
    },
    {
      "answer": "To 'cry unto the Lord' is more than reciting a prayer. It's a heartfelt, desperate plea born out of deep need and reliance on God. It involves pouring out your soul, expressing your fears and vulnerabilities, and humbly seeking his intervention.",
      "question": "Q2: What does it mean to 'cry unto the Lord'? Is it just saying a prayer?"
    },
    {
      "answer": "God's allowing trouble doesn't negate his love. Suffering can refine us, teach us dependence on Him, and strengthen our character. It also allows us to empathize with others and demonstrate God's compassion in a broken world. Ultimately, suffering points to our need for redemption.",
      "question": "Q3: If God is loving, why does he allow us to experience 'trouble' and 'distress' in the first place?"
    },
    {
      "answer": "Psalm 107:6 has both personal and broader applications. Just as individuals cry out, nations and the world can also appeal to God during crises. The verse inspires collective prayer for justice, peace, and healing, reflecting God's concern for all creation.",
      "question": "Q4: Can Psalm 107:6 be applied to national or global crises, or is it just for personal problems?"
    },
    {
      "answer": "Assurance comes from God's promises. Hebrews 4:16 encourages us to approach God's throne boldly, knowing we'll find grace. Faith believes God hears based on scripture, even when feelings are absent. Persistent prayer strengthens that confidence.",
      "question": "Q5: How can I be sure that God is listening when I 'cry unto the Lord'?"
    }
  ],
  "popularity_score": 0,
  "exportedAt": "2026-02-20T16:42:50.132Z"
}