{
  "id": 15920,
  "book": "Psalms",
  "chapter": 107,
  "verse": 15,
  "slug": "psalms-107-15",
  "testament": "Old Testament",
  "text": "Oh that men would praise the LORD for his goodness, and for his wonderful works to the children of men!",
  "text_kjv": "Oh that men would praise the LORD for his goodness, and for his wonderful works to the children of men!",
  "text_niv": "Let them give thanks to the Lord for his unfailing loveand his wonderful deeds for men,",
  "text_esv": "Let them thank the LORD for his steadfast love, for his wondrous works to the children of man!",
  "text_nlt": "Let them praise the LORD for his great loveand for the wonderful things he has done for them.",
  "text_msg": "So thank God for his marvelous love,for his miracle mercy to the children he loves;",
  "text_nasb": "Let them give thanks to the LORD for His lovingkindness, And for His wonders to the sons of men!",
  "context": "Psalm 107 is a psalm of thanksgiving, specifically celebrating God's deliverance of his people from various predicaments. Understanding the historical and cultural context of this psalm helps us appreciate the depth of the psalmist's call to praise. The psalm likely originated after the Babylonian exile, when the Jewish people were returning to their homeland. The repeated refrain, including verse 15, highlights the importance of grateful acknowledgment of God's saving actions. The four scenarios depicted – wandering in the desert, imprisonment, illness, and storms at sea – resonate with the collective memory of the Israelites' experiences of hardship and God's subsequent intervention throughout their history. The imagery of the desert evokes the wilderness wanderings after the Exodus from Egypt, a time of testing and dependence on God's provision. Imprisonment could refer to the exile itself or other periods of oppression. Illness was often understood as a consequence of sin, making healing a sign of God's favor and forgiveness. The storms at sea were a common metaphor for life's challenges and God's power to calm the chaos. The inclusion of 'the children of men' suggests a broader application beyond just the Israelites; God's goodness is extended to all humanity. The psalm uses evocative language to paint vivid pictures of both the distress and the deliverance, emphasizing the contrast between human helplessness and divine power. The psalm's structure, with its recurring pattern of trouble, cry for help, deliverance, and call to praise, reinforces the central message of gratitude and reliance on God.",
  "meaning": "Psalm 107:15, “Oh that men would praise the LORD for his goodness, and for his wonderful works to the children of men!” encapsulates the core theological message of the entire psalm. It's a heartfelt desire, almost a lament, that humanity would recognize and respond appropriately to God's benevolent nature and his miraculous interventions. The phrase “his goodness” refers to God's inherent character, his consistent kindness, and his unwavering love. It’s not just about isolated acts of mercy but the very essence of God's being. “Wonderful works” points to the specific instances where God has intervened in human affairs, performing miracles, providing deliverance, and demonstrating his power. These aren’t random occurrences but deliberate acts of grace intended to reveal God's character and his concern for his creation. The phrase “children of men” broadens the scope of God’s goodness beyond just the Israelites. It emphasizes that God's love and his acts of salvation are available to all people, regardless of their background or ethnicity. The repetition of this verse (and similar refrains) throughout the psalm serves to underscore its importance. It's a call to worship, a challenge to complacency, and a reminder of the reciprocal relationship between God and humanity. The theological significance lies in the understanding that God is not distant or indifferent but actively involved in the lives of his people, offering salvation and blessing. The verse is also a recognition that praising God is the appropriate response to his goodness and a way of acknowledging his sovereignty and worth. It also emphasizes that humankind should turn towards praising and glorifying God instead of remaining self-centered. It reinforces the idea that gratitude is a foundational virtue in the life of faith.",
  "application": "Psalm 107:15 challenges us to cultivate a lifestyle of gratitude in our modern context. In a world often focused on individual achievement and material possessions, it's easy to overlook the many blessings we receive daily. This verse calls us to intentionally recognize and acknowledge God's goodness in our lives. Practically, this means taking time each day to reflect on specific ways God has shown his favor. It could be simple things like a safe journey, a supportive friend, or a beautiful sunset. We can express our gratitude through prayer, telling God directly how thankful we are for his provision. We can also express our gratitude to others, acknowledging their contributions to our lives and demonstrating appreciation for their kindness. Furthermore, this verse calls us to actively seek out and share stories of God's “wonderful works.” This could involve sharing testimonies in church, posting encouraging messages on social media, or simply telling others about how God has intervened in our lives. By sharing these stories, we not only encourage others but also reinforce our own faith and gratitude. It also urges us to see beyond our immediate circumstances and recognize God's hand at work in the world around us. This might involve supporting organizations that are working to alleviate suffering, advocating for justice, or simply showing compassion to those in need. By actively participating in God's work, we demonstrate our gratitude for his goodness and his wonderful works. In a society often marked by negativity and cynicism, choosing gratitude is a powerful act of resistance. It's a way of affirming God's presence and power in our lives and of inspiring others to do the same. It means intentionally shifting our focus from what we lack to what we have, and from what is wrong to what is right. By embodying the spirit of Psalm 107:15, we can transform our lives and the lives of those around us, creating a culture of gratitude that honors God and blesses others.",
  "prayer": "Heavenly Father, I come before you with a heart longing to praise you more fully. Forgive me for the times I have taken your goodness for granted and have failed to acknowledge your wonderful works in my life. Open my eyes to see your blessings all around me – in the simple joys, the answered prayers, and the unexpected mercies. Help me to cultivate a spirit of gratitude that overflows from my heart and into my actions. Teach me to be a faithful witness to your grace, sharing your stories with others and pointing them to your unwavering love. May my life be a testament to your goodness, drawing others closer to you. Lord, remind me daily of your steadfast love, even when I face challenges and uncertainties. Help me trust in your promises and to rest in your peace, knowing that you are always with me. I offer you my praise and adoration, trusting that you will continue to work wonders in my life and in the lives of those I love. In Jesus' name, Amen.",
  "faqs": [
    {
      "answer": "The term 'men' in the original Hebrew is better understood as humankind or humanity. It's a general call to all people, both male and female, to acknowledge and praise God for his goodness and works. The emphasis is on universal participation in worship, not a restriction to a specific gender.",
      "question": "Q1 about this verse: Why does the psalm emphasize the need for *men* to praise God?"
    },
    {
      "answer": "The 'wonderful works' are vast and varied, encompassing creation, redemption, provision, healing, and deliverance. Specifically, it can include answered prayers, miraculous interventions, acts of kindness, and any demonstration of God's power and love in our lives and in the world around us.",
      "question": "Q2: What are some specific 'wonderful works' of God that people should praise Him for?"
    },
    {
      "answer": "Praising God shifts our focus from our problems to His power and provision. This change in perspective cultivates gratitude and opens our hearts to recognize and receive even more of His blessings. It strengthens our faith and deepens our relationship with Him.",
      "question": "Q3: How does praising God connect to experiencing more of His goodness?"
    },
    {
      "answer": "Yes, absolutely. Praise is an act of obedience and a declaration of faith, even when feelings are absent. Choosing to praise God, even when we don't feel like it, can actually lead to a shift in our emotions and a renewed sense of gratitude and joy.",
      "question": "Q4: If I don't *feel* thankful, is it still important to praise God?"
    },
    {
      "answer": "Model gratitude yourself! Regularly thank God in prayer for blessings, share stories of His faithfulness, and encourage children to express their own thanks. Make praising God a natural and joyful part of your family life through song, prayer, and service.",
      "question": "Q5: How can I teach my children the importance of praising God, as Psalm 107:15 suggests?"
    }
  ],
  "popularity_score": 0,
  "exportedAt": "2026-02-20T16:42:50.133Z"
}