{
  "id": 15875,
  "book": "Psalms",
  "chapter": 106,
  "verse": 18,
  "slug": "psalms-106-18",
  "testament": "Old Testament",
  "text": "And a fire was kindled in their company; the flame burned up the wicked.",
  "text_kjv": "And a fire was kindled in their company; the flame burned up the wicked.",
  "text_niv": "Fire blazed among their followers;a flame consumed the wicked.",
  "text_esv": "Fire also broke out in their company; the flame burned up the wicked.",
  "text_nlt": "Fire fell upon their followers;a flame consumed the wicked.",
  "text_msg": "Fire flared against that rebel crewand torched them to a cinder.",
  "text_nasb": "And a fire blazed up in their company; The flame consumed the wicked.",
  "context": "Psalm 106 is a historical psalm, a lament, and a confession of Israel's sins during the Exodus and subsequent wanderings in the wilderness. Verse 18 specifically refers to the incident at Taberah, described in Numbers 11:1-3. The Israelites, having grown weary and dissatisfied with the manna provided by God, complained bitterly about their hardships. Their grumbling and craving for meat demonstrated a profound lack of faith and gratitude towards God's provision and protection after their miraculous deliverance from Egyptian slavery. The 'mixed multitude' who had left Egypt with them (Exodus 12:38) likely stirred up this discontent. This group was not fully committed to the covenant with God and yearned for the perceived comforts of Egypt, influencing the Israelites. The word 'Taberah' itself means 'burning,' a direct reference to the fire sent by God as judgment upon their sin. The fire's specific origin is described as coming from the Lord. This was not accidental or natural, but a direct act of divine retribution. The Israelites' sin was not merely a matter of taste preferences; it was an act of rebellion against God's authority and a rejection of His provision. This rebellion echoed the earlier idolatry in Egypt and foreshadowed the repeated instances of disobedience that plagued Israel throughout their history. The fire consumed 'the outskirts of the camp,' indicating the pervasive nature of the discontent and the severity of God's displeasure. The people cried out to Moses, who interceded with the Lord, and the fire was quenched, highlighting the role of mediation in averting divine wrath.",
  "meaning": "Psalm 106:18 carries significant theological weight, illustrating the immediate and just consequences of sin. The 'fire' represents God's holy wrath against unrepentant rebellion. It underscores the seriousness with which God views disobedience, particularly when it involves rejecting His provision and questioning His goodness. The phrase 'burned up the wicked' suggests a separation between the righteous and the unrighteous, even within the Israelite community. While the entire nation suffered the consequences of their collective sin (the fire reached the outskirts of the camp), the wicked, specifically those who instigated and actively participated in the rebellion, bore the brunt of God's judgment. This concept aligns with the broader Old Testament theme of divine justice and accountability. The incident at Taberah serves as a microcosm of Israel's repeated failures and God's consistent faithfulness, even in the face of their unfaithfulness. The fact that the fire was quenched through Moses' intercession points to the importance of mediation and the potential for repentance to avert divine judgment. This foreshadows the ultimate mediation of Jesus Christ, who intercedes on behalf of humanity, offering forgiveness and reconciliation with God. The fire also serves as a symbolic warning. It reminds believers that sin, even seemingly small acts of discontent and ingratitude, can ignite a destructive force in their lives and communities. This verse highlights the need for constant vigilance, self-examination, and a humble dependence on God's grace to avoid the pitfalls of rebellion and the consequences of divine displeasure. It demonstrates that God's patience has limits and that unrepentant sin incurs His righteous judgment.",
  "application": "Psalm 106:18 offers several practical applications for modern believers. Firstly, it serves as a potent reminder to cultivate gratitude for God's provision in our lives. Just as the Israelites grew weary of manna, we can easily take God's blessings for granted. We must consciously acknowledge and appreciate the blessings, both large and small, in our lives – our health, our families, our homes, and our opportunities. Secondly, we must be vigilant against the spirit of discontent and complaining. The Israelites' grumbling stemmed from a lack of trust in God's plan and a desire for something more. This same spirit can manifest in our lives through dissatisfaction with our circumstances, envy of others, or a constant craving for more material possessions. Instead of complaining, we should practice contentment and trust in God's wisdom and timing. Thirdly, we need to examine our own hearts for hidden rebellion. Sin often begins with small acts of disobedience or a refusal to submit to God's will. We must be honest with ourselves and confess our sins to God, seeking His forgiveness and guidance. Regular self-reflection and prayer can help us identify and address these tendencies before they escalate. Fourthly, we are called to intercede for others. Just as Moses interceded for the Israelites, we should pray for those who are struggling with sin, rebellion, or discontentment. Our prayers can make a difference in their lives and help them turn back to God. Fifthly, we should be mindful of the influence of negative voices. The 'mixed multitude' stirred up discontent among the Israelites. We must be discerning about the voices we allow to influence us, choosing to surround ourselves with people who encourage faith, obedience, and gratitude. Finally, we should remember that God's grace is available to us. Even when we stumble and fall, we can turn to God for forgiveness and restoration. His mercy endures forever, and He is always willing to help us get back on the right path.",
  "prayer": "Heavenly Father, forgive us for the times we have been ungrateful and discontent. Forgive us for taking Your blessings for granted and for complaining about our circumstances. Help us to cultivate hearts of gratitude and to trust in Your provision. Search our hearts, Lord, and reveal any hidden rebellion or sin that we need to confess. Grant us the strength to resist the temptation to complain and to choose instead to rejoice in Your goodness. Give us wisdom to discern the voices that influence us and to surround ourselves with those who encourage faith and obedience. Help us to intercede for those who are struggling with sin and discontentment. Thank you for Your endless mercy and grace, and for the promise of forgiveness and restoration. In Jesus' name, we pray. Amen.",
  "faqs": [
    {
      "answer": "The fire symbolized God's holy judgment against their blatant rejection of His provision and leadership. It was not merely a matter of being picky eaters; it was rebellion against God's authority and a lack of faith in His promises after He had delivered them from slavery.",
      "question": "Q1: Why did God send fire in response to their complaining?"
    },
    {
      "answer": "It suggests that those who were the instigators and core participants in the rebellion suffered more directly. It highlights that while the whole community faced consequences, the specifically wicked bore the brunt of divine justice.",
      "question": "Q2: What does 'burned up the wicked' mean in this context?"
    },
    {
      "answer": "Practice daily thankfulness. Keep a gratitude journal, intentionally notice blessings, and verbally express appreciation to God and others. Challenge complaining thoughts with reminders of God's faithfulness.",
      "question": "Q3: How can I avoid the sin of ingratitude in my own life?"
    },
    {
      "answer": "Moses' intercession demonstrated the power of prayer. It highlights that God often responds to the prayers of the righteous, showing that intercessory prayer can be a vital component in averting judgment and obtaining mercy.",
      "question": "Q4: What role does intercession play in averting God's judgment?"
    },
    {
      "answer": "It foreshadows the ultimate intercession of Jesus, who offers forgiveness for sin and reconciles us to God. It shows the need for ongoing repentance and awareness of the consequences of rejecting God.",
      "question": "Q5: How does this verse relate to the New Testament?"
    }
  ],
  "popularity_score": 0,
  "exportedAt": "2026-02-20T16:42:50.125Z"
}